data_test/__init__.py
data_test/data_test.py
data_test/dimensions.py
data_test/measures.py
pelive_data_test-0.2.dev0.dist-info/METADATA
pelive_data_test-0.2.dev0.dist-info/RECORD
pelive_data_test-0.2.dev0.dist-info/WHEEL
pelive_data_test-0.2.dev0.dist-info/top_level.txt
