Metadata-Version: 2.1
Name: pelive-data-test
Version: 0.2.dev0
Summary: UNKNOWN
Home-page: http://www.google.com
Author: UNKNOWN
Author-email: UNKNOWN
License: MIT
Platform: UNKNOWN
Requires-Dist: requests
Requires-Dist: pandas
Requires-Dist: pandas
